langstrothclient/__init__.py
langstrothclient/client.py
langstrothclient/constants.py
langstrothclient/osc/__init__.py
langstrothclient/osc/plugin.py
langstrothclient/osc/v1/__init__.py
langstrothclient/osc/v1/outages.py
langstrothclient/tests/__init__.py
langstrothclient/tests/unit/__init__.py
langstrothclient/tests/unit/fakes.py
langstrothclient/tests/unit/utils.py
langstrothclient/tests/unit/v1/__init__.py
langstrothclient/tests/unit/v1/fakes.py
langstrothclient/tests/unit/v1/test_outages.py
langstrothclient/v1/__init__.py
langstrothclient/v1/client.py
langstrothclient/v1/outages.py
langstrothclient-0.8.0.dist-info/DESCRIPTION.rst
langstrothclient-0.8.0.dist-info/METADATA
langstrothclient-0.8.0.dist-info/RECORD
langstrothclient-0.8.0.dist-info/WHEEL
langstrothclient-0.8.0.dist-info/entry_points.txt
langstrothclient-0.8.0.dist-info/metadata.json
langstrothclient-0.8.0.dist-info/top_level.txt
