Metadata-Version: 2.0
Name: langstrothclient
Version: 0.8.0
Summary: Client for the Nectar Operations system (Langstroth)
Home-page: https://github.com/NeCTAR-RC/python-langstrothclient
Author: Stephen Crawley
Author-email: stephen.crawley@ardc.edu.au
License: Apache
Platform: UNKNOWN
Classifier: License :: OSI Approved :: Apache Software License
Classifier: Programming Language :: Python :: 3
Classifier: Operating System :: OS Independent
Requires-Dist: keystoneauth1
Requires-Dist: nectarclient-lib (<2.0.0,>=1.0.0)
Requires-Dist: osc-lib
Requires-Dist: oslo.utils
Requires-Dist: pbr
Requires-Dist: requests
